neuralqa/__init__.py
neuralqa/cli.py
neuralqa/config_default.yaml
neuralqa/version.py
neuralqa/expander/__init__.py
neuralqa/expander/expander.py
neuralqa/expander/expanderpool.py
neuralqa/expander/mlmexpander.py
neuralqa/reader/__init__.py
neuralqa/reader/bertreader.py
neuralqa/reader/reader.py
neuralqa/reader/readerpool.py
neuralqa/retriever/__init__.py
neuralqa/retriever/elasticsearchretriever.py
neuralqa/retriever/retriever.py
neuralqa/retriever/retrieverpool.py
neuralqa/retriever/solrretriever.py
neuralqa/server/__init__.py
neuralqa/server/routehandlers.py
neuralqa/server/routemodels.py
neuralqa/server/serve.py
neuralqa/server/server_app.py
neuralqa/server/test_query.py
neuralqa/server/ui/build/.DS_Store
neuralqa/server/ui/build/android-chrome-192x192.png
neuralqa/server/ui/build/android-chrome-512x512.png
neuralqa/server/ui/build/apple-touch-icon.png
neuralqa/server/ui/build/asset-manifest.json
neuralqa/server/ui/build/favicon-16x16.png
neuralqa/server/ui/build/favicon-32x32.png
neuralqa/server/ui/build/favicon.ico
neuralqa/server/ui/build/index.html
neuralqa/server/ui/build/logo152.png
neuralqa/server/ui/build/manifest.json
neuralqa/server/ui/build/precache-manifest.f2ddb522e87f24d57699361b5d062612.js
neuralqa/server/ui/build/robots.txt
neuralqa/server/ui/build/service-worker.js
neuralqa/server/ui/build/images/icon.png
neuralqa/server/ui/build/libs/.DS_Store
neuralqa/server/ui/build/libs/leader-line.min.js
neuralqa/server/ui/build/static/css/main.0d7f6602.chunk.css
neuralqa/server/ui/build/static/css/main.0d7f6602.chunk.css.map
neuralqa/server/ui/build/static/js/2.17f05cd8.chunk.js
neuralqa/server/ui/build/static/js/2.17f05cd8.chunk.js.LICENSE.txt
neuralqa/server/ui/build/static/js/2.17f05cd8.chunk.js.map
neuralqa/server/ui/build/static/js/main.32abfeaf.chunk.js
neuralqa/server/ui/build/static/js/main.32abfeaf.chunk.js.map
neuralqa/server/ui/build/static/js/runtime-main.985d1449.js
neuralqa/server/ui/build/static/js/runtime-main.985d1449.js.map
neuralqa-0.0.31a0.dist-info/LICENSE
neuralqa-0.0.31a0.dist-info/METADATA
neuralqa-0.0.31a0.dist-info/WHEEL
neuralqa-0.0.31a0.dist-info/entry_points.txt
neuralqa-0.0.31a0.dist-info/top_level.txt
neuralqa-0.0.31a0.dist-info/RECORD
