Metadata-Version: 2.1
Name: neuralqa
Version: 0.0.31a0
Summary: NeuralQA: Question Answering on Large Datasets
Home-page: https://github.com/victordibia/neuralqa
Author: Victor Dibia
License: MIT
Keywords: NLP,Question Answering,Machine Learning
Platform: UNKNOWN
Classifier: Development Status :: 3 - Alpha
Classifier: Intended Audience :: Developers
Classifier: License :: OSI Approved :: MIT License
Classifier: Programming Language :: Python :: 3.6
Requires-Python: >=3.5
Requires-Dist: fastapi
Requires-Dist: aiofiles
Requires-Dist: uvicorn
Requires-Dist: numpy
Requires-Dist: tensorflow (>=2.1.0)
Requires-Dist: torch
Requires-Dist: torchvision
Requires-Dist: transformers
Requires-Dist: elasticsearch (>=7.7.1)
Requires-Dist: pyyaml (>=3.13)
Requires-Dist: spacy
Provides-Extra: test
Requires-Dist: pytest ; extra == 'test'
